cosmosetl/__init__.py
cosmosetl/__main__.py
cosmosetl/get_block.py
cosmosetl/json_rpc_requests.py
cosmosetl/thread_local_proxy.py
cosmosetl/utils.py
cosmosetl/cli/__init__.py
cosmosetl/cli/export_blocks.py
cosmosetl/cli/export_transactions_and_events.py
cosmosetl/cli/get_block_range_for_date.py
cosmosetl/cli/get_block_range_for_timestamps.py
cosmosetl/domain/__init__.py
cosmosetl/domain/block.py
cosmosetl/domain/event.py
cosmosetl/domain/transaction.py
cosmosetl/jobs/__init__.py
cosmosetl/jobs/export_blocks_job.py
cosmosetl/jobs/export_transactions_job.py
cosmosetl/jobs/exporters/__init__.py
cosmosetl/jobs/exporters/blocks_item_exporter.py
cosmosetl/jobs/exporters/transactions_and_events_item_exporter.py
cosmosetl/mappers/__init__.py
cosmosetl/mappers/block_mapper.py
cosmosetl/mappers/event_mapper.py
cosmosetl/mappers/transaction_mapper.py
cosmosetl/providers/__init__.py
cosmosetl/providers/auto.py
cosmosetl/providers/ipc.py
cosmosetl/providers/rpc.py
cosmosetl/service/__init__.py
cosmosetl/service/cosm_service.py
cosmosetl/service/graph_operations.py
cosmos_etl-0.0.2.dist-info/LICENSE
cosmos_etl-0.0.2.dist-info/METADATA
cosmos_etl-0.0.2.dist-info/WHEEL
cosmos_etl-0.0.2.dist-info/entry_points.txt
cosmos_etl-0.0.2.dist-info/top_level.txt
cosmos_etl-0.0.2.dist-info/RECORD
