Metadata-Version: 2.1
Name: cosmos-etl
Version: 0.0.2
Summary: Tools for exporting Cosmos blockchain data to CSV or JSON
Home-page: https://github.com/bizzyvinci/cosmos-etl
Author: Bisola Olasehinde
Author-email: horlasehinde@gmail.com
Project-URL: Bug Reports, https://github.com/bizzyvinci/cosmos-etl/issues
Project-URL: Source, https://github.com/bizzyvinci/cosmos-etl
Keywords: cosmos,tendermint
Classifier: Development Status :: 4 - Beta
Classifier: Intended Audience :: Developers
Classifier: License :: OSI Approved :: MIT License
Classifier: Programming Language :: Python :: 3
Classifier: Programming Language :: Python :: 3.7
Classifier: Programming Language :: Python :: 3.8
Classifier: Programming Language :: Python :: 3.9
Requires-Python: >=3.7.2,<4
License-File: LICENSE
Requires-Dist: blockchain-etl-common
Requires-Dist: web3 (<6,>=5.29)
